LICENSE
MANIFEST.in
README.rst
setup.py
lastfm/__init__.py
lastfm/exceptions.py
lastfm/info.py
lastfm/lfm.py
lfmh.egg-info/PKG-INFO
lfmh.egg-info/SOURCES.txt
lfmh.egg-info/dependency_links.txt
lfmh.egg-info/requires.txt
lfmh.egg-info/top_level.txt