Metadata-Version: 1.1
Name: lfmh
Version: 1.1.0
Summary: A Last.fm API interface.
Home-page: https://bitbucket.org/hauzer/lfm/
Author: Никола "hauzer" Вукосављевић
Author-email: hauzer@gmx.com
License: GPLv3
Download-URL: https://bitbucket.org/hauzer/lfm/downloads
Platform: UNKNOWN
Classifier: Development Status :: 4 - Beta
Classifier: Intended Audience :: Developers
Classifier: License :: OSI Approved :: GNU General Public License v3 (GPLv3)
Classifier: Operating System :: OS Independent
Classifier: Programming Language :: Python :: 3
Classifier: Topic :: Software Development :: Libraries
